dashi/__init__.py
dashi/_constants.py
dashi/utils.py
dashi/supervised_characterization/__init__.py
dashi/supervised_characterization/arrange_metrics.py
dashi/supervised_characterization/estimate_models.py
dashi/supervised_characterization/plot_performance.py
dashi/unsupervised_characterization/__init__.py
dashi/unsupervised_characterization/utils.py
dashi/unsupervised_characterization/data_source_map/__init__.py
dashi/unsupervised_characterization/data_source_map/data_source_map.py
dashi/unsupervised_characterization/data_source_map/data_source_map_plotter.py
dashi/unsupervised_characterization/data_temporal_map/__init__.py
dashi/unsupervised_characterization/data_temporal_map/data_temporal_map.py
dashi/unsupervised_characterization/data_temporal_map/data_temporal_map_plotter.py
dashi/unsupervised_characterization/variability_metrics/__init__.py
dashi/unsupervised_characterization/variability_metrics/estimate_msv_metrics.py
dashi/unsupervised_characterization/variability_metrics/igt_plotting.py
dashi/unsupervised_characterization/variability_metrics/igt_projection.py
dashi/unsupervised_characterization/variability_metrics/igt_projection_estimator.py
dashi/unsupervised_characterization/variability_metrics/igt_trajectory_estimator.py
dashi/unsupervised_characterization/variability_metrics/plot_msv.py
dashi-0.2.3.dist-info/licenses/LICENSE
dashi-0.2.3.dist-info/licenses/NOTICE
dashi-0.2.3.dist-info/METADATA
dashi-0.2.3.dist-info/WHEEL
dashi-0.2.3.dist-info/top_level.txt
dashi-0.2.3.dist-info/RECORD
