Metadata-Version: 2.4
Name: dashi
Version: 0.2.3
Summary: Dataset shift analysis and characterization in python
Author-email: "David Fernández-Narro (UPV), Pablo Ferri Borredá (UPV), Ángel Sánchez-García (UPV), Juan M García-Gómez (UPV), Carlos Sáez (UPV); Biomedical Data Science Lab, ITACA Institute, Universitat Politècnica de València, Spain" <carsaesi@upv.es>
License: Apache-2.0
Project-URL: Homepage, https://github.com/bdslab-upv/dashi
Project-URL: Documentation, https://github.com/bdslab-upv/dashi/docs
Project-URL: Source, https://github.com/bdslab-upv/dashi
Project-URL: Tracker, https://github.com/bdslab-upv/dashi/issues
Project-URL: License of Reference, https://github.com/hms-dbmi/EHRtemporalVariability/blob/master/LICENSE
Keywords: dashi,dataset shift,machine learning,artificial intelligence,exploratory analysis,time,source,variability
Classifier: Programming Language :: Python :: 3.10
Classifier: Programming Language :: Python :: 3.11
Classifier: Programming Language :: Python :: 3.12
Classifier: Programming Language :: Python :: 3 :: Only
Classifier: License :: OSI Approved :: Apache Software License
Classifier: Operating System :: OS Independent
Classifier: Intended Audience :: Science/Research
Classifier: Topic :: Scientific/Engineering
Classifier: Topic :: Scientific/Engineering :: Information Analysis
Classifier: Topic :: Scientific/Engineering :: Artificial Intelligence
Classifier: Topic :: Software Development :: Libraries
Classifier: Topic :: Software Development :: Libraries :: Python Modules
Requires-Python: >=3.10
License-File: LICENSE
License-File: NOTICE
Requires-Dist: numpy>=1.26.1
Requires-Dist: pandas>=2.2.2
Requires-Dist: plotly==5.18.0
Requires-Dist: scikit-learn==1.5.1
Requires-Dist: python-dateutil>=2.8.2
Requires-Dist: tqdm>=4.66.5
Requires-Dist: prince>=0.14.0
Dynamic: license-file
